package_name/__init__.py
package_name/file1_name.py
package_name/file2_name.py
pacote_imagem_simples_python-0.0.1.dist-info/METADATA
pacote_imagem_simples_python-0.0.1.dist-info/WHEEL
pacote_imagem_simples_python-0.0.1.dist-info/top_level.txt
pacote_imagem_simples_python-0.0.1.dist-info/RECORD
