Metadata-Version: 2.1
Name: pacote_imagem_simples_python
Version: 0.0.1
Summary: Projeto Dio. Python NTT DATA
Home-page: https://github.com/carloscamposb/proceesamento_imagem_python
Author: Carlos Campos
Author-email: carloscampos.bn@gmail.com
Requires-Dist: matplotlib
Requires-Dist: numpy
Requires-Dist: scikit-image >=0.16.1
